odoo/addons/purchase_order_line_sequence/README.rst
odoo/addons/purchase_order_line_sequence/__init__.py
odoo/addons/purchase_order_line_sequence/__manifest__.py
odoo/addons/purchase_order_line_sequence/i18n/de.po
odoo/addons/purchase_order_line_sequence/i18n/es.po
odoo/addons/purchase_order_line_sequence/i18n/fr.po
odoo/addons/purchase_order_line_sequence/i18n/purchase_order_line_sequence.pot
odoo/addons/purchase_order_line_sequence/models/__init__.py
odoo/addons/purchase_order_line_sequence/models/account_move_line.py
odoo/addons/purchase_order_line_sequence/models/purchase.py
odoo/addons/purchase_order_line_sequence/models/purchase_line.py
odoo/addons/purchase_order_line_sequence/models/stock_move.py
odoo/addons/purchase_order_line_sequence/readme/CONTRIBUTORS.rst
odoo/addons/purchase_order_line_sequence/readme/DESCRIPTION.rst
odoo/addons/purchase_order_line_sequence/readme/ROADMAP.rst
odoo/addons/purchase_order_line_sequence/readme/USAGE.rst
odoo/addons/purchase_order_line_sequence/static/description/icon.png
odoo/addons/purchase_order_line_sequence/static/description/index.html
odoo/addons/purchase_order_line_sequence/tests/__init__.py
odoo/addons/purchase_order_line_sequence/tests/test_po_lines_sequence.py
odoo/addons/purchase_order_line_sequence/views/account_move_view.xml
odoo/addons/purchase_order_line_sequence/views/purchase_view.xml
odoo/addons/purchase_order_line_sequence/views/report_invoice.xml
odoo/addons/purchase_order_line_sequence/views/report_purchaseorder.xml
odoo/addons/purchase_order_line_sequence/views/report_purchasequotation.xml
odoo14_addon_purchase_order_line_sequence-14.0.2.0.0.dist-info/METADATA
odoo14_addon_purchase_order_line_sequence-14.0.2.0.0.dist-info/WHEEL
odoo14_addon_purchase_order_line_sequence-14.0.2.0.0.dist-info/top_level.txt
odoo14_addon_purchase_order_line_sequence-14.0.2.0.0.dist-info/RECORD
